Metadata-Version: 2.1
Name: ytstudio
Version: 1.5.2
Summary: Unofficial API for Youtube Studio.
Home-page: https://github.com/yusufusta/ytstudio
Author: Yusuf Usta
Author-email: yusuf@usta.email
Maintainer: Yusuf Usta
Maintainer-email: yusuf@usta.email
License: GPL3
Keywords: youtube,youtube-studio,ytstudio,studio
Platform: UNKNOWN
Classifier: Intended Audience :: Developers
Classifier: License :: OSI Approved :: GNU General Public License v3 (GPLv3)
Classifier: Programming Language :: Python :: 3.7
Classifier: Programming Language :: Python :: 3.8
Classifier: Programming Language :: Python :: 3.9
Classifier: Programming Language :: Python :: 3.10
License-File: LICENSE
